uniovi_simur_wearablepermed_utils-1.21.0.dist-info/licenses/LICENSE.txt
wearablepermed_utils/__init__.py
wearablepermed_utils/aggregate_windows_features.py
wearablepermed_utils/clean_dataset_folder.py
wearablepermed_utils/csv_to_segmented_activity.py
wearablepermed_utils/model_aggregation.py
wearablepermed_utils/plot.py
wearablepermed_utils/segmented_activity_to_stack.py
wearablepermed_utils/sensor_bin_to_csv.py
wearablepermed_utils/skeleton.py
wearablepermed_utils/stack_to_features.py
wearablepermed_utils/core/__init__.py
wearablepermed_utils/core/_autocalibration.py
wearablepermed_utils/core/_bin2csv_0616.py
wearablepermed_utils/core/_data_augmentation.py
wearablepermed_utils/core/_feature_extraction.py
wearablepermed_utils/core/_file_management.py
wearablepermed_utils/core/_plot.py
wearablepermed_utils/core/_preprocessing.py
wearablepermed_utils/core/_segmentation.py
uniovi_simur_wearablepermed_utils-1.21.0.dist-info/METADATA
uniovi_simur_wearablepermed_utils-1.21.0.dist-info/WHEEL
uniovi_simur_wearablepermed_utils-1.21.0.dist-info/entry_points.txt
uniovi_simur_wearablepermed_utils-1.21.0.dist-info/top_level.txt
uniovi_simur_wearablepermed_utils-1.21.0.dist-info/RECORD
